kucoin/__init__.py
kucoin/client.py
kucoin/exceptions.py
kucoin_python_aio-1.0.0.dist-info/LICENSE
kucoin_python_aio-1.0.0.dist-info/METADATA
kucoin_python_aio-1.0.0.dist-info/WHEEL
kucoin_python_aio-1.0.0.dist-info/top_level.txt
kucoin_python_aio-1.0.0.dist-info/RECORD
