Metadata-Version: 2.1
Name: kucoin-python-aio
Version: 1.0.0
Summary: Kucoin API Client For V2
Home-page: https://github.com/huangjacky/python-kucoin
Author: HuangJacky
Author-email: huangjacky@163.com
License: MIT
Keywords: kucoin api btc eth kcs usdt
Platform: UNKNOWN
Classifier: Intended Audience :: Developers
Classifier: License :: OSI Approved :: MIT License
Classifier: Operating System :: OS Independent
Classifier: Programming Language :: Python :: 3
Classifier: Programming Language :: Python :: 3.4
Classifier: Programming Language :: Python :: 3.5
Classifier: Programming Language :: Python :: 3.6
Classifier: Programming Language :: Python :: 3.7
Classifier: Programming Language :: Python
Classifier: Topic :: Software Development :: Libraries :: Python Modules
Requires-Dist: aiohttp
